<?xml version="1.0" encoding="UTF-8" standalone="yes"?>
<w:document xmlns:wpc="http://schemas.microsoft.com/office/word/2010/wordprocessingCanvas" xmlns:mo="http://schemas.microsoft.com/office/mac/office/2008/main" xmlns:mc="http://schemas.openxmlformats.org/markup-compatibility/2006" xmlns:mv="urn:schemas-microsoft-com:mac:vml" xmlns:o="urn:schemas-microsoft-com:office:office" xmlns:r="http://schemas.openxmlformats.org/officeDocument/2006/relationships" xmlns:m="http://schemas.openxmlformats.org/officeDocument/2006/math" xmlns:v="urn:schemas-microsoft-com:vml" xmlns:wp14="http://schemas.microsoft.com/office/word/2010/wordprocessingDrawing" xmlns:wp="http://schemas.openxmlformats.org/drawingml/2006/wordprocessingDrawing" xmlns:w10="urn:schemas-microsoft-com:office:word" xmlns:w="http://schemas.openxmlformats.org/wordprocessingml/2006/main" xmlns:w14="http://schemas.microsoft.com/office/word/2010/wordml" xmlns:w15="http://schemas.microsoft.com/office/word/2012/wordml" xmlns:wpg="http://schemas.microsoft.com/office/word/2010/wordprocessingGroup" xmlns:wpi="http://schemas.microsoft.com/office/word/2010/wordprocessingInk" xmlns:wne="http://schemas.microsoft.com/office/word/2006/wordml" xmlns:wps="http://schemas.microsoft.com/office/word/2010/wordprocessingShape" mc:Ignorable="w14 w15 wp14"><w:body><w:p w14:paraId="73EF7557" w14:textId="77777777" w:rsidR="00DA5426" w:rsidRPr="00AA2588" w:rsidRDefault="00DA5426" w:rsidP="006B4359"><w:pPr><w:tabs><w:tab w:val="right" w:pos="8640"/></w:tabs><w:spacing w:after="0"/><w:jc w:val="right"/><w:outlineLvl w:val="0"/><w:rPr><w:rFonts w:ascii="Arial Narrow" w:hAnsi="Arial Narrow" w:cs="Arial"/><w:kern w:val="0"/><w:sz w:val="32"/><w:szCs w:val="32"/><w:lang w:eastAsia="en-US"/></w:rPr></w:pPr><w:r><w:rPr><w:rFonts w:ascii="Arial Narrow" w:hAnsi="Arial Narrow" w:cs="Arial"/><w:kern w:val="0"/><w:sz w:val="32"/><w:szCs w:val="32"/><w:lang w:eastAsia="en-US"/></w:rPr><w:t>V</w:t></w:r><w:r w:rsidR="00FF0A98"><w:rPr><w:rFonts w:ascii="Arial Narrow" w:hAnsi="Arial Narrow" w:cs="Arial"/><w:kern w:val="0"/><w:sz w:val="32"/><w:szCs w:val="32"/><w:lang w:eastAsia="en-US"/></w:rPr><w:t>2_CONFORM_R1</w:t></w:r><w:r w:rsidR="00A8113E"><w:rPr><w:rFonts w:ascii="Arial Narrow" w:hAnsi="Arial Narrow" w:cs="Arial"/><w:kern w:val="0"/><w:sz w:val="32"/><w:szCs w:val="32"/><w:lang w:eastAsia="en-US"/></w:rPr><w:t>_</w:t></w:r><w:r w:rsidR="009F0D95"><w:rPr><w:rFonts w:ascii="Arial Narrow" w:hAnsi="Arial Narrow" w:cs="Arial"/><w:kern w:val="0"/><w:sz w:val="32"/><w:szCs w:val="32"/><w:lang w:eastAsia="en-US"/></w:rPr><w:t>O1_</w:t></w:r><w:r w:rsidR="00A8113E"><w:rPr><w:rFonts w:ascii="Arial Narrow" w:hAnsi="Arial Narrow" w:cs="Arial"/><w:kern w:val="0"/><w:sz w:val="32"/><w:szCs w:val="32"/><w:lang w:eastAsia="en-US"/></w:rPr><w:t>2019</w:t></w:r><w:r w:rsidR="00B63EEC"><w:rPr><w:rFonts w:ascii="Arial Narrow" w:hAnsi="Arial Narrow" w:cs="Arial"/><w:kern w:val="0"/><w:sz w:val="32"/><w:szCs w:val="32"/><w:lang w:eastAsia="en-US"/></w:rPr><w:t>SEPT</w:t></w:r></w:p><w:p w14:paraId="44758E1B" w14:textId="77777777" w:rsidR="00DA5426" w:rsidRPr="005E5207" w:rsidRDefault="00DA5426" w:rsidP="00DA5426"><w:pPr><w:tabs><w:tab w:val="right" w:pos="8640"/></w:tabs><w:spacing w:after="0"/><w:rPr><w:rFonts w:ascii="Arial Narrow" w:hAnsi="Arial Narrow" w:cs="Arial"/><w:kern w:val="0"/><w:sz w:val="32"/><w:szCs w:val="32"/><w:lang w:eastAsia="en-US"/></w:rPr></w:pPr></w:p><w:p w14:paraId="6CD97341" w14:textId="77777777" w:rsidR="00103634" w:rsidRPr="00103634" w:rsidRDefault="00103634" w:rsidP="00103634"><w:pPr><w:tabs><w:tab w:val="right" w:pos="8640"/></w:tabs><w:spacing w:before="0" w:after="0"/><w:jc w:val="left"/><w:rPr><w:rFonts w:ascii="Arial Narrow" w:hAnsi="Arial Narrow" w:cs="Arial"/><w:kern w:val="0"/><w:sz w:val="32"/><w:szCs w:val="32"/><w:lang w:eastAsia="en-US"/></w:rPr></w:pPr><w:bookmarkStart w:id="0" w:name="_Hlk506304285"/><w:bookmarkEnd w:id="0"/><w:r><w:rPr><w:rFonts w:ascii="Arial Narrow" w:hAnsi="Arial Narrow" w:cs="Arial"/><w:noProof/><w:kern w:val="0"/><w:sz w:val="32"/><w:szCs w:val="32"/><w:lang w:eastAsia="zh-CN"/></w:rPr><w:drawing><wp:inline distT="0" distB="0" distL="0" distR="0" wp14:anchorId="22306A2D" wp14:editId="36661731"><wp:extent cx="2228850" cy="1209675"/><wp:effectExtent l="19050" t="0" r="0" b="0"/><wp:docPr id="45" name="Picture 7" descr="HL7_lg"/><wp:cNvGraphicFramePr><a:graphicFrameLocks xmlns:a="http://schemas.openxmlformats.org/drawingml/2006/main" noChangeAspect="1"/></wp:cNvGraphicFramePr><a:graphic xmlns:a="http://schemas.openxmlformats.org/drawingml/2006/main"><a:graphicData uri="http://schemas.openxmlformats.org/drawingml/2006/picture"><pic:pic xmlns:pic="http://schemas.openxmlformats.org/drawingml/2006/picture"><pic:nvPicPr><pic:cNvPr id="0" name="Picture 7" descr="HL7_lg"/><pic:cNvPicPr><a:picLocks noChangeAspect="1" noChangeArrowheads="1"/></pic:cNvPicPr></pic:nvPicPr><pic:blipFill><a:blip r:embed="rId8" cstate="print"/><a:srcRect/><a:stretch><a:fillRect/></a:stretch></pic:blipFill><pic:spPr bwMode="auto"><a:xfrm><a:off x="0" y="0"/><a:ext cx="2228850" cy="1209675"/></a:xfrm><a:prstGeom prst="rect"><a:avLst/></a:prstGeom><a:noFill/><a:ln w="9525"><a:noFill/><a:miter lim="800000"/><a:headEnd/><a:tailEnd/></a:ln></pic:spPr></pic:pic></a:graphicData></a:graphic></wp:inline></w:drawing></w:r></w:p><w:p w14:paraId="6D276F75" w14:textId="77777777" w:rsidR="00103634" w:rsidRPr="00103634" w:rsidRDefault="00103634" w:rsidP="00103634"><w:pPr><w:tabs><w:tab w:val="right" w:pos="8640"/></w:tabs><w:spacing w:before="0" w:after="0"/><w:jc w:val="left"/><w:rPr><w:rFonts w:ascii="Arial Narrow" w:hAnsi="Arial Narrow" w:cs="Arial"/><w:kern w:val="0"/><w:sz w:val="32"/><w:szCs w:val="32"/><w:lang w:eastAsia="en-US"/></w:rPr></w:pPr></w:p><w:p w14:paraId="1CEBDC9C" w14:textId="77777777" w:rsidR="00103634" w:rsidRPr="00103634" w:rsidRDefault="00103634" w:rsidP="00103634"><w:pPr><w:spacing w:before="0" w:after="0"/><w:jc w:val="right"/><w:rPr><w:rFonts w:ascii="Arial Narrow" w:hAnsi="Arial Narrow" w:cs="Arial"/><w:kern w:val="0"/><w:sz w:val="32"/><w:szCs w:val="32"/><w:lang w:val="de-DE" w:eastAsia="en-US"/></w:rPr></w:pPr></w:p><w:p w14:paraId="1F7AFEF3" w14:textId="77777777" w:rsidR="00103634" w:rsidRPr="00103634" w:rsidRDefault="00103634" w:rsidP="00103634"><w:pPr><w:spacing w:before="0" w:after="0"/><w:jc w:val="center"/><w:rPr><w:kern w:val="0"/><w:lang w:eastAsia="en-US"/></w:rPr></w:pPr></w:p><w:p w14:paraId="4C93858C" w14:textId="77777777" w:rsidR="00DA5426" w:rsidRPr="00655E67" w:rsidRDefault="00DA5426" w:rsidP="00DA5426"><w:pPr><w:spacing w:after="0"/><w:jc w:val="center"/><w:rPr><w:kern w:val="0"/><w:lang w:eastAsia="en-US"/></w:rPr></w:pPr></w:p><w:p w14:paraId="52771A75" w14:textId="77777777" w:rsidR="00DA5426" w:rsidRPr="005E5207" w:rsidRDefault="00AD38F4" w:rsidP="00DA5426"><w:pPr><w:spacing w:after="0"/><w:jc w:val="right"/><w:rPr><w:rFonts w:ascii="Arial" w:hAnsi="Arial"/><w:b/><w:kern w:val="0"/><w:sz w:val="36"/><w:szCs w:val="36"/><w:u w:val="single"/><w:lang w:eastAsia="en-US"/></w:rPr></w:pPr><w:r><w:rPr><w:rFonts w:ascii="Arial" w:hAnsi="Arial"/><w:b/><w:kern w:val="0"/><w:sz w:val="36"/><w:szCs w:val="36"/><w:u w:val="single"/><w:lang w:eastAsia="en-US"/></w:rPr><w:t>HL7 Version 2</w:t></w:r><w:r w:rsidR="00DA5426"><w:rPr><w:rFonts w:ascii="Arial" w:hAnsi="Arial"/><w:b/><w:kern w:val="0"/><w:sz w:val="36"/><w:szCs w:val="36"/><w:u w:val="single"/><w:lang w:eastAsia="en-US"/></w:rPr><w:t xml:space="preserve"> Conformance</w:t></w:r><w:r w:rsidR="00E15B31"><w:rPr><w:rFonts w:ascii="Arial" w:hAnsi="Arial"/><w:b/><w:kern w:val="0"/><w:sz w:val="36"/><w:szCs w:val="36"/><w:u w:val="single"/><w:lang w:eastAsia="en-US"/></w:rPr><w:t xml:space="preserve"> Methodology</w:t></w:r><w:r w:rsidR="00DA5426" w:rsidRPr="00DA42BC"><w:rPr><w:rFonts w:ascii="Arial" w:hAnsi="Arial"/><w:b/><w:kern w:val="0"/><w:sz w:val="36"/><w:szCs w:val="36"/><w:u w:val="single"/><w:lang w:eastAsia="en-US"/></w:rPr><w:t xml:space="preserve"> </w:t></w:r><w:r w:rsidR="00DA5426" w:rsidRPr="00DA42BC"><w:rPr><w:rFonts w:ascii="Arial" w:hAnsi="Arial"/><w:b/><w:kern w:val="0"/><w:sz w:val="36"/><w:szCs w:val="36"/><w:u w:val="single"/><w:lang w:eastAsia="en-US"/></w:rPr><w:br/></w:r><w:r w:rsidR="00DA5426"><w:rPr><w:rFonts w:ascii="Arial" w:hAnsi="Arial"/><w:b/><w:kern w:val="0"/><w:sz w:val="36"/><w:szCs w:val="36"/><w:u w:val="single"/><w:lang w:eastAsia="en-US"/></w:rPr><w:t xml:space="preserve">Release 1 </w:t></w:r></w:p><w:p w14:paraId="3E3EE919" w14:textId="77777777" w:rsidR="00DA5426" w:rsidRPr="00236E3E" w:rsidRDefault="00E6078E" w:rsidP="00DA5426"><w:pPr><w:spacing w:after="0"/><w:jc w:val="right"/><w:rPr><w:kern w:val="0"/><w:sz w:val="36"/><w:szCs w:val="36"/><w:lang w:eastAsia="en-US"/></w:rPr></w:pPr><w:r><w:rPr><w:kern w:val="0"/><w:sz w:val="36"/><w:szCs w:val="36"/><w:lang w:eastAsia="en-US"/></w:rPr><w:t>September</w:t></w:r><w:r w:rsidR="00DA5426" w:rsidRPr="002F0B20"><w:rPr><w:kern w:val="0"/><w:sz w:val="36"/><w:szCs w:val="36"/><w:lang w:eastAsia="en-US"/></w:rPr><w:t xml:space="preserve"> </w:t></w:r><w:r w:rsidR="00A8113E"><w:rPr><w:kern w:val="0"/><w:sz w:val="36"/><w:szCs w:val="36"/><w:lang w:eastAsia="en-US"/></w:rPr><w:t>2019</w:t></w:r></w:p><w:p w14:paraId="0E8141D2" w14:textId="77777777" w:rsidR="00DA5426" w:rsidRPr="00655E67" w:rsidRDefault="00DA5426" w:rsidP="00DA5426"><w:pPr><w:spacing w:after="0"/><w:jc w:val="right"/><w:rPr><w:kern w:val="0"/><w:sz w:val="36"/><w:szCs w:val="36"/><w:lang w:eastAsia="en-US"/></w:rPr></w:pPr></w:p><w:p w14:paraId="0FC6D1AF" w14:textId="77777777" w:rsidR="00DA5426" w:rsidRPr="00655E67" w:rsidRDefault="00DA5426" w:rsidP="006B4359"><w:pPr><w:spacing w:after="0"/><w:jc w:val="right"/><w:outlineLvl w:val="0"/><w:rPr><w:b/><w:kern w:val="0"/><w:sz w:val="36"/><w:szCs w:val="36"/><w:lang w:eastAsia="en-US"/></w:rPr></w:pPr><w:r><w:rPr><w:b/><w:kern w:val="0"/><w:sz w:val="36"/><w:szCs w:val="36"/><w:lang w:eastAsia="en-US"/></w:rPr><w:t xml:space="preserve">HL7 </w:t></w:r><w:r w:rsidR="00A53287"><w:rPr><w:b/><w:kern w:val="0"/><w:sz w:val="36"/><w:szCs w:val="36"/><w:lang w:eastAsia="en-US"/></w:rPr><w:t>Draft</w:t></w:r><w:r w:rsidRPr="00655E67"><w:rPr><w:b/><w:kern w:val="0"/><w:sz w:val="36"/><w:szCs w:val="36"/><w:lang w:eastAsia="en-US"/></w:rPr><w:t xml:space="preserve"> </w:t></w:r><w:r w:rsidR="00103634"><w:rPr><w:b/><w:kern w:val="0"/><w:sz w:val="36"/><w:szCs w:val="36"/><w:lang w:eastAsia="en-US"/></w:rPr><w:t xml:space="preserve">for Comment </w:t></w:r><w:r w:rsidRPr="00655E67"><w:rPr><w:b/><w:kern w:val="0"/><w:sz w:val="36"/><w:szCs w:val="36"/><w:lang w:eastAsia="en-US"/></w:rPr><w:t>Ballot</w:t></w:r><w:r w:rsidR="00A53287"><w:rPr><w:b/><w:kern w:val="0"/><w:sz w:val="36"/><w:szCs w:val="36"/><w:lang w:eastAsia="en-US"/></w:rPr><w:t xml:space="preserve"> </w:t></w:r></w:p><w:p w14:paraId="5966E97C" w14:textId="77777777" w:rsidR="00DA5426" w:rsidRPr="00655E67" w:rsidRDefault="00DA5426" w:rsidP="00DA5426"><w:pPr><w:spacing w:after="0"/><w:rPr><w:kern w:val="0"/><w:lang w:eastAsia="en-US"/></w:rPr></w:pPr></w:p><w:p w14:paraId="5C181BC1" w14:textId="77777777" w:rsidR="00DA5426" w:rsidRPr="00655E67" w:rsidRDefault="00DA5426" w:rsidP="00DA5426"><w:pPr><w:spacing w:after="0"/><w:jc w:val="right"/><w:rPr><w:b/><w:kern w:val="0"/><w:lang w:eastAsia="en-US"/></w:rPr></w:pPr><w:r w:rsidRPr="00655E67"><w:rPr><w:b/><w:kern w:val="0"/><w:lang w:eastAsia="en-US"/></w:rPr><w:t>Sponsored by:</w:t></w:r><w:r w:rsidRPr="00655E67"><w:rPr><w:b/><w:kern w:val="0"/><w:lang w:eastAsia="en-US"/></w:rPr><w:br/></w:r><w:r><w:rPr><w:b/><w:kern w:val="0"/><w:lang w:eastAsia="en-US"/></w:rPr><w:t>Conformance</w:t></w:r><w:r w:rsidRPr="00655E67"><w:rPr><w:b/><w:kern w:val="0"/><w:lang w:eastAsia="en-US"/></w:rPr><w:t xml:space="preserve"> Work Group </w:t></w:r></w:p><w:p w14:paraId="23ED8F8F" w14:textId="77777777" w:rsidR="00DA5426" w:rsidRPr="00655E67" w:rsidRDefault="00DA5426" w:rsidP="00DA5426"><w:pPr><w:spacing w:after="0"/><w:jc w:val="right"/><w:rPr><w:b/><w:kern w:val="0"/><w:lang w:eastAsia="en-US"/></w:rPr></w:pPr></w:p><w:p w14:paraId="6BA92F9F" w14:textId="77777777" w:rsidR="00DA5426" w:rsidRPr="00655E67" w:rsidRDefault="00DA5426" w:rsidP="00AD38F4"><w:pPr><w:rPr><w:kern w:val="0"/><w:lang w:eastAsia="en-US"/></w:rPr></w:pPr></w:p><w:tbl><w:tblPr><w:tblW w:w="9360" w:type="dxa"/><w:jc w:val="center"/><w:tblBorders><w:top w:val="single" w:sz="12" w:space="0" w:color="CC3300"/><w:left w:val="single" w:sz="4" w:space="0" w:color="C0C0C0"/><w:bottom w:val="single" w:sz="12" w:space="0" w:color="CC3300"/><w:right w:val="single" w:sz="4" w:space="0" w:color="C0C0C0"/><w:insideH w:val="single" w:sz="12" w:space="0" w:color="CC3300"/><w:insideV w:val="single" w:sz="4" w:space="0" w:color="C0C0C0"/></w:tblBorders><w:tblLayout w:type="fixed"/><w:tblLook w:val="0000" w:firstRow="0" w:lastRow="0" w:firstColumn="0" w:lastColumn="0" w:noHBand="0" w:noVBand="0"/></w:tblPr><w:tblGrid><w:gridCol w:w="3780"/><w:gridCol w:w="5580"/></w:tblGrid><w:tr w:rsidR="00DA5426" w:rsidRPr="00655E67" w14:paraId="277F6335" w14:textId="77777777" w:rsidTr="00AD38F4"><w:trPr><w:jc w:val="center"/></w:trPr><w:tc><w:tcPr><w:tcW w:w="3780" w:type="dxa"/></w:tcPr><w:p w14:paraId="5494DC53" w14:textId="77777777" w:rsidR="00DA5426" w:rsidRPr="00655E67" w:rsidRDefault="00DA5426" w:rsidP="00AD38F4"><w:pPr><w:pStyle w:val="TableContent"/><w:jc w:val="left"/><w:rPr><w:lang w:eastAsia="de-DE"/></w:rPr></w:pPr><w:r><w:t>Conformance Co-chair: Principle Author</w:t></w:r></w:p></w:tc><w:tc><w:tcPr><w:tcW w:w="5580" w:type="dxa"/></w:tcPr><w:p w14:paraId="6DD535D7" w14:textId="77777777" w:rsidR="00DA5426" w:rsidRPr="00655E67" w:rsidRDefault="00DA5426" w:rsidP="00AD38F4"><w:pPr><w:pStyle w:val="TableContent"/><w:jc w:val="left"/><w:rPr><w:lang w:eastAsia="de-DE"/></w:rPr></w:pPr><w:r><w:t xml:space="preserve">Robert Snelick, </w:t></w:r><w:r w:rsidRPr="0047783E"><w:t xml:space="preserve">National Institute of Standards and Technology </w:t></w:r><w:r><w:t>(NIST)</w:t></w:r></w:p></w:tc></w:tr><w:tr w:rsidR="00DA5426" w:rsidRPr="00655E67" w14:paraId="159CE654" w14:textId="77777777" w:rsidTr="00AD38F4"><w:trPr><w:jc w:val="center"/></w:trPr><w:tc><w:tcPr><w:tcW w:w="3780" w:type="dxa"/></w:tcPr><w:p w14:paraId="5D0DA385" w14:textId="77777777" w:rsidR="00DA5426" w:rsidRPr="00655E67" w:rsidRDefault="00DA5426" w:rsidP="00AD38F4"><w:pPr><w:pStyle w:val="TableContent"/><w:jc w:val="left"/><w:rPr><w:lang w:eastAsia="de-DE"/></w:rPr></w:pPr><w:r><w:t>Conformance Co-chair</w:t></w:r></w:p></w:tc><w:tc><w:tcPr><w:tcW w:w="5580" w:type="dxa"/></w:tcPr><w:p w14:paraId="6F471927" w14:textId="77777777" w:rsidR="00DA5426" w:rsidRPr="00655E67" w:rsidRDefault="00DA5426" w:rsidP="00AD38F4"><w:pPr><w:pStyle w:val="TableContent"/><w:jc w:val="left"/><w:rPr><w:lang w:eastAsia="de-DE"/></w:rPr></w:pPr><w:r><w:t>Frank Oemig</w:t></w:r><w:r w:rsidR="0042351B"><w:t xml:space="preserve">, </w:t></w:r><w:r w:rsidR="0042351B"><w:rPr><w:noProof/></w:rPr><w:t>Deutsche Telekom Healthcare Security Solutions GmbH</w:t></w:r></w:p></w:tc></w:tr><w:tr w:rsidR="00DA5426" w:rsidRPr="00655E67" w14:paraId="2D3E0D4A" w14:textId="77777777" w:rsidTr="00AD38F4"><w:trPr><w:jc w:val="center"/></w:trPr><w:tc><w:tcPr><w:tcW w:w="3780" w:type="dxa"/></w:tcPr><w:p w14:paraId="3F3CF36A" w14:textId="77777777" w:rsidR="00DA5426" w:rsidRPr="00655E67" w:rsidRDefault="00DA5426" w:rsidP="00AD38F4"><w:pPr><w:pStyle w:val="TableContent"/><w:jc w:val="left"/><w:rPr><w:lang w:eastAsia="de-DE"/></w:rPr></w:pPr><w:r w:rsidRPr="00414768"><w:t>Conformance Co-chair</w:t></w:r></w:p></w:tc><w:tc><w:tcPr><w:tcW w:w="5580" w:type="dxa"/></w:tcPr><w:p w14:paraId="20530D9D" w14:textId="77777777" w:rsidR="00DA5426" w:rsidRPr="00655E67" w:rsidRDefault="00DA5426" w:rsidP="00AD38F4"><w:pPr><w:pStyle w:val="TableContent"/><w:jc w:val="left"/><w:rPr><w:lang w:eastAsia="de-DE"/></w:rPr></w:pPr><w:r><w:t>Nathan Bunker, American Immunization Registry Association (AIRA)</w:t></w:r></w:p></w:tc></w:tr><w:tr w:rsidR="00DA5426" w:rsidRPr="00655E67" w14:paraId="66261AE9" w14:textId="77777777" w:rsidTr="00AD38F4"><w:trPr><w:jc w:val="center"/></w:trPr><w:tc><w:tcPr><w:tcW w:w="3780" w:type="dxa"/></w:tcPr><w:p w14:paraId="40908DC6" w14:textId="77777777" w:rsidR="00DA5426" w:rsidRPr="00655E67" w:rsidRDefault="00DA5426" w:rsidP="00AD38F4"><w:pPr><w:pStyle w:val="TableContent"/><w:jc w:val="left"/><w:rPr><w:lang w:eastAsia="de-DE"/></w:rPr></w:pPr><w:r w:rsidRPr="00414768"><w:t>Conformance Co-chair</w:t></w:r></w:p></w:tc><w:tc><w:tcPr><w:tcW w:w="5580" w:type="dxa"/></w:tcPr><w:p w14:paraId="049BC01F" w14:textId="77777777" w:rsidR="00DA5426" w:rsidRPr="00655E67" w:rsidRDefault="00DA5426" w:rsidP="00AD38F4"><w:pPr><w:pStyle w:val="TableContent"/><w:jc w:val="left"/><w:rPr><w:lang w:eastAsia="de-DE"/></w:rPr></w:pPr><w:r><w:t>Ioana S</w:t></w:r><w:r w:rsidR="00E40AAB"><w:t>ingureanu</w:t></w:r><w:r w:rsidR="00DE0376"><w:t>, Eversolve, LLC</w:t></w:r></w:p></w:tc></w:tr></w:tbl><w:p w14:paraId="5EE33894" w14:textId="77777777" w:rsidR="00DA5426" w:rsidRPr="00655E67" w:rsidRDefault="00DA5426" w:rsidP="00DA5426"><w:pPr><w:jc w:val="right"/><w:rPr><w:kern w:val="0"/><w:sz w:val="20"/><w:szCs w:val="20"/><w:lang w:eastAsia="en-US"/></w:rPr></w:pPr></w:p><w:p w14:paraId="4DFE8119" w14:textId="77777777" w:rsidR="00DA5426" w:rsidRPr="00DA42BC" w:rsidRDefault="00DA5426" w:rsidP="00DA5426"><w:pPr><w:rPr><w:kern w:val="0"/><w:sz w:val="20"/><w:szCs w:val="20"/><w:lang w:eastAsia="en-US"/></w:rPr></w:pPr><w:r w:rsidRPr="00655E67"><w:rPr><w:b/><w:bCs/><w:sz w:val="20"/><w:szCs w:val="20"/></w:rPr><w:t>Questions or comments regarding this document should be directe</w:t></w:r><w:r><w:rPr><w:b/><w:bCs/><w:sz w:val="20"/><w:szCs w:val="20"/></w:rPr><w:t>d to the Conformance</w:t></w:r><w:r w:rsidRPr="00655E67"><w:rPr><w:b/><w:bCs/><w:sz w:val="20"/><w:szCs w:val="20"/></w:rPr><w:t xml:space="preserve"> Workgroup (</w:t></w:r><w:hyperlink r:id="rId9" w:history="1"><w:r w:rsidRPr="003D6C3A"><w:rPr><w:rStyle w:val="Hyperlink"/><w:rFonts w:ascii="Times New Roman" w:hAnsi="Times New Roman"/></w:rPr><w:t>cgit@lists.hl7.org</w:t></w:r></w:hyperlink><w:r w:rsidRPr="00655E67"><w:rPr><w:b/><w:bCs/><w:sz w:val="20"/><w:szCs w:val="20"/></w:rPr><w:t>)</w:t></w:r><w:r w:rsidRPr="00DA42BC"><w:rPr><w:rFonts w:ascii="Arial" w:hAnsi="Arial" w:cs="Arial"/><w:b/><w:bCs/><w:sz w:val="20"/><w:szCs w:val="20"/></w:rPr><w:t>.</w:t></w:r></w:p><w:p w14:paraId="37AB752C" w14:textId="77777777" w:rsidR="00DA5426" w:rsidRPr="00AA2588" w:rsidRDefault="00DA5426" w:rsidP="00DA5426"><w:pPr><w:spacing w:after="100"/><w:rPr><w:kern w:val="0"/><w:sz w:val="20"/><w:szCs w:val="20"/><w:lang w:eastAsia="en-US"/></w:rPr></w:pPr></w:p><w:p w14:paraId="47BAF1B3" w14:textId="77777777" w:rsidR="00DA5426" w:rsidRPr="005E5207" w:rsidRDefault="00DA5426" w:rsidP="00DA5426"><w:pPr><w:spacing w:after="100"/><w:rPr><w:kern w:val="0"/><w:sz w:val="20"/><w:szCs w:val="20"/><w:lang w:eastAsia="en-US"/></w:rPr></w:pPr></w:p><w:p w14:paraId="69D73C43" w14:textId="77777777" w:rsidR="00DA5426" w:rsidRPr="002F0B20" w:rsidRDefault="00DA5426" w:rsidP="00DA5426"><w:pPr><w:spacing w:after="100"/><w:rPr><w:kern w:val="0"/><w:sz w:val="20"/><w:szCs w:val="20"/><w:lang w:eastAsia="en-US"/></w:rPr></w:pPr></w:p><w:p w14:paraId="012FC730" w14:textId="77777777" w:rsidR="00DA5426" w:rsidRPr="00236E3E" w:rsidRDefault="00DA5426" w:rsidP="00DA5426"><w:pPr><w:spacing w:after="100"/><w:rPr><w:kern w:val="0"/><w:sz w:val="20"/><w:szCs w:val="20"/><w:lang w:eastAsia="en-US"/></w:rPr></w:pPr></w:p><w:p w14:paraId="20F91EAF" w14:textId="77777777" w:rsidR="00DA5426" w:rsidRPr="00655E67" w:rsidRDefault="00DA5426" w:rsidP="00DA5426"><w:pPr><w:spacing w:after="100"/><w:rPr><w:b/><w:kern w:val="0"/><w:sz w:val="18"/><w:szCs w:val="18"/><w:lang w:eastAsia="en-US"/></w:rPr></w:pPr><w:r w:rsidRPr="00655E67"><w:rPr><w:color w:val="000000"/><w:kern w:val="0"/><w:sz w:val="18"/><w:szCs w:val="18"/><w:lang w:eastAsia="en-US"/></w:rPr><w:t>Copyright © 201</w:t></w:r><w:r w:rsidR="00A8113E"><w:rPr><w:color w:val="000000"/><w:kern w:val="0"/><w:sz w:val="18"/><w:szCs w:val="18"/><w:lang w:eastAsia="en-US"/></w:rPr><w:t>9</w:t></w:r><w:r w:rsidRPr="00655E67"><w:rPr><w:color w:val="000000"/><w:kern w:val="0"/><w:sz w:val="18"/><w:szCs w:val="18"/><w:lang w:eastAsia="en-US"/></w:rPr><w:t xml:space="preserve"> Health Level Seven International ® ALL RIGHTS RESERVED. </w:t></w:r><w:r w:rsidRPr="00655E67"><w:rPr><w:kern w:val="0"/><w:sz w:val="18"/><w:szCs w:val="18"/><w:lang w:eastAsia="en-US"/></w:rPr><w:t xml:space="preserve">The reproduction of this material in any form is strictly forbidden without the written permission of the publisher. </w:t></w:r><w:r w:rsidRPr="00655E67"><w:rPr><w:color w:val="000000"/><w:kern w:val="0"/><w:sz w:val="18"/><w:szCs w:val="18"/><w:lang w:eastAsia="en-US"/></w:rPr><w:t>HL7 and Health Level Seven are registered trademarks of Health Level Seven International. Reg. U.S. Pat &amp; TM Off</w:t></w:r><w:r w:rsidRPr="00655E67"><w:rPr><w:b/><w:kern w:val="0"/><w:sz w:val="18"/><w:szCs w:val="18"/><w:lang w:eastAsia="en-US"/></w:rPr><w:t>.</w:t></w:r></w:p><w:p w14:paraId="101AD36E" w14:textId="77777777" w:rsidR="00DA5426" w:rsidRDefault="00DA5426" w:rsidP="00DA5426"><w:pPr><w:spacing w:after="100"/><w:rPr><w:color w:val="000000"/><w:kern w:val="0"/><w:sz w:val="18"/><w:szCs w:val="18"/><w:lang w:eastAsia="en-US"/></w:rPr></w:pPr><w:r w:rsidRPr="00655E67"><w:rPr><w:color w:val="000000"/><w:kern w:val="0"/><w:sz w:val="18"/><w:szCs w:val="18"/><w:lang w:eastAsia="en-US"/></w:rPr><w:t xml:space="preserve">Use of this material is governed by HL7's </w:t></w:r><w:hyperlink r:id="rId10" w:history="1"><w:r w:rsidRPr="00DA42BC"><w:rPr><w:b/><w:color w:val="333399"/><w:kern w:val="0"/><w:sz w:val="18"/><w:u w:val="single"/><w:lang w:eastAsia="zh-CN"/></w:rPr><w:t>IP Compliance Policy</w:t></w:r></w:hyperlink><w:r w:rsidRPr="00655E67"><w:rPr><w:color w:val="000000"/><w:kern w:val="0"/><w:sz w:val="18"/><w:szCs w:val="18"/><w:lang w:eastAsia="en-US"/></w:rPr><w:t>.</w:t></w:r></w:p><w:p w14:paraId="702DD63F" w14:textId="77777777" w:rsidR="00103634" w:rsidRDefault="00103634"><w:pPr><w:rPr><w:color w:val="000000"/><w:kern w:val="0"/><w:sz w:val="18"/><w:szCs w:val="18"/><w:lang w:eastAsia="en-US"/></w:rPr></w:pPr><w:r><w:rPr><w:color w:val="000000"/><w:kern w:val="0"/><w:sz w:val="18"/><w:szCs w:val="18"/><w:lang w:eastAsia="en-US"/></w:rPr><w:br w:type="page"/></w:r></w:p><w:p w14:paraId="298128AF" w14:textId="77777777" w:rsidR="00103634" w:rsidRPr="0019015F" w:rsidRDefault="00103634" w:rsidP="006B4359"><w:pPr><w:pStyle w:val="Default"/><w:outlineLvl w:val="0"/><w:rPr><w:sz w:val="18"/><w:szCs w:val="18"/></w:rPr></w:pPr><w:r><w:rPr><w:b/><w:bCs/><w:sz w:val="22"/><w:szCs w:val="22"/></w:rPr><w:lastRenderedPageBreak/><w:t>I</w:t></w:r><w:r w:rsidRPr="0019015F"><w:rPr><w:b/><w:bCs/><w:sz w:val="18"/><w:szCs w:val="18"/></w:rPr><w:t xml:space="preserve">MPORTANT NOTES: </w:t></w:r></w:p><w:p w14:paraId="5B02921F" w14:textId="77777777" w:rsidR="00103634" w:rsidRPr="0019015F" w:rsidRDefault="00103634" w:rsidP="00103634"><w:pPr><w:pStyle w:val="Default"/><w:rPr><w:sz w:val="18"/><w:szCs w:val="18"/></w:rPr></w:pPr><w:r w:rsidRPr="0019015F"><w:rPr><w:sz w:val="18"/><w:szCs w:val="18"/></w:rPr><w:t xml:space="preserve">HL7 licenses its standards and select IP free of charge. </w:t></w:r><w:r w:rsidRPr="0019015F"><w:rPr><w:b/><w:bCs/><w:sz w:val="18"/><w:szCs w:val="18"/></w:rPr><w:t xml:space="preserve">If you did not acquire a free license from HL7 for this document, </w:t></w:r><w:r w:rsidRPr="0019015F"><w:rPr><w:sz w:val="18"/><w:szCs w:val="18"/></w:rPr><w:t xml:space="preserve">you are not authorized to access or make any use of it. To obtain a free license, please visit http://www.HL7.org/implement/standards/index.cfm. </w:t></w:r></w:p><w:p w14:paraId="0CAC9338" w14:textId="77777777" w:rsidR="00103634" w:rsidRPr="0019015F" w:rsidRDefault="00103634" w:rsidP="00103634"><w:pPr><w:pStyle w:val="Default"/><w:rPr><w:sz w:val="18"/><w:szCs w:val="18"/></w:rPr></w:pPr><w:r w:rsidRPr="0019015F"><w:rPr><w:b/><w:bCs/><w:sz w:val="18"/><w:szCs w:val="18"/></w:rPr><w:t>If you are the individual that obtained the license for this HL7 Standard, specification or other freely licensed work (in each and every instance "Specified Material")</w:t></w:r><w:r w:rsidRPr="0019015F"><w:rPr><w:sz w:val="18"/><w:szCs w:val="18"/></w:rPr><w:t xml:space="preserve">, the following describes the permitted uses of the Material. </w:t></w:r></w:p><w:p w14:paraId="53988AA8" w14:textId="77777777" w:rsidR="00103634" w:rsidRPr="0019015F" w:rsidRDefault="00103634" w:rsidP="00103634"><w:pPr><w:pStyle w:val="Default"/><w:rPr><w:sz w:val="18"/><w:szCs w:val="18"/></w:rPr></w:pPr><w:r w:rsidRPr="0019015F"><w:rPr><w:b/><w:bCs/><w:sz w:val="18"/><w:szCs w:val="18"/></w:rPr><w:t xml:space="preserve">A. HL7 INDIVIDUAL, STUDENT AND HEALTH PROFESSIONAL MEMBERS, </w:t></w:r><w:r w:rsidRPr="0019015F"><w:rPr><w:sz w:val="18"/><w:szCs w:val="18"/></w:rPr><w:t xml:space="preserve">who register and agree to the terms of HL7’s license, are authorized, without additional charge, to read, and to use Specified Material to develop and sell products and services that implement, but do not directly incorporate, the Specified Material in whole or in part without paying license fees to HL7. </w:t></w:r></w:p><w:p w14:paraId="1E0C3B88" w14:textId="77777777" w:rsidR="00103634" w:rsidRPr="0019015F" w:rsidRDefault="00103634" w:rsidP="00103634"><w:pPr><w:pStyle w:val="Default"/><w:rPr><w:sz w:val="18"/><w:szCs w:val="18"/></w:rPr></w:pPr><w:r w:rsidRPr="0019015F"><w:rPr><w:sz w:val="18"/><w:szCs w:val="18"/></w:rPr><w:t xml:space="preserve">INDIVIDUAL, STUDENT AND HEALTH PROFESSIONAL MEMBERS wishing to incorporate additional items of Special Material in whole or part, into products and services, or to enjoy additional authorizations granted to HL7 ORGANIZATIONAL MEMBERS as noted below, must become ORGANIZATIONAL MEMBERS of HL7. </w:t></w:r></w:p><w:p w14:paraId="5654847B" w14:textId="77777777" w:rsidR="00103634" w:rsidRPr="0019015F" w:rsidRDefault="00103634" w:rsidP="00103634"><w:pPr><w:pStyle w:val="Default"/><w:rPr><w:sz w:val="18"/><w:szCs w:val="18"/></w:rPr></w:pPr><w:r w:rsidRPr="0019015F"><w:rPr><w:b/><w:bCs/><w:sz w:val="18"/><w:szCs w:val="18"/></w:rPr><w:t xml:space="preserve">B. HL7 ORGANIZATION MEMBERS, </w:t></w:r><w:r w:rsidRPr="0019015F"><w:rPr><w:sz w:val="18"/><w:szCs w:val="18"/></w:rPr><w:t xml:space="preserve">who register and agree to the terms of HL7's License, are authorized, without additional charge, on a perpetual (except as provided for in the full license terms governing the Material), non-exclusive and worldwide basis, the right to (a) download, copy (for internal purposes only) and share this Material with your employees and consultants for study purposes, and (b) utilize the Material for the purpose of developing, making, having made, using, marketing, importing, offering to sell or license, and selling or licensing, and to otherwise distribute, Compliant Products, in all cases subject to the conditions set forth in this Agreement and any relevant patent and other intellectual property rights of third parties (which may include members of HL7). No other license, sublicense, or other rights of any kind are granted under this Agreement. </w:t></w:r></w:p><w:p w14:paraId="036B45BE" w14:textId="77777777" w:rsidR="00103634" w:rsidRPr="0019015F" w:rsidRDefault="00103634" w:rsidP="00103634"><w:pPr><w:pStyle w:val="Default"/><w:rPr><w:sz w:val="18"/><w:szCs w:val="18"/></w:rPr></w:pPr><w:r w:rsidRPr="0019015F"><w:rPr><w:b/><w:bCs/><w:sz w:val="18"/><w:szCs w:val="18"/></w:rPr><w:t xml:space="preserve">C. NON-MEMBERS, </w:t></w:r><w:r w:rsidRPr="0019015F"><w:rPr><w:sz w:val="18"/><w:szCs w:val="18"/></w:rPr><w:t xml:space="preserve">who register and agree to the terms of HL7’s IP policy for Specified Material, are authorized, without additional charge, to read and use the Specified Material for evaluating whether to implement, or in implementing, the Specified Material, and to use Specified Material to develop and sell products and services that implement, but do not directly incorporate, the Specified Material in whole or in part. </w:t></w:r></w:p><w:p w14:paraId="455F4272" w14:textId="77777777" w:rsidR="00103634" w:rsidRPr="00103634" w:rsidRDefault="00103634" w:rsidP="00103634"><w:pPr><w:pStyle w:val="Default"/><w:rPr><w:sz w:val="18"/><w:szCs w:val="18"/></w:rPr></w:pPr><w:r w:rsidRPr="00103634"><w:rPr><w:sz w:val="18"/><w:szCs w:val="18"/></w:rPr><w:t xml:space="preserve">NON-MEMBERS wishing to incorporate additional items of Specified Material in whole or part, into products and services, or to enjoy the additional authorizations granted to HL7 ORGANIZATIONAL MEMBERS, as noted above, must become ORGANIZATIONAL MEMBERS of HL7. </w:t></w:r></w:p><w:p w14:paraId="7284E0A2" w14:textId="77777777" w:rsidR="00103634" w:rsidRPr="00103634" w:rsidRDefault="00103634" w:rsidP="00103634"><w:pPr><w:rPr><w:rFonts w:ascii="Arial" w:hAnsi="Arial" w:cs="Arial"/><w:sz w:val="18"/><w:szCs w:val="18"/></w:rPr></w:pPr><w:r w:rsidRPr="00103634"><w:rPr><w:rFonts w:ascii="Arial" w:hAnsi="Arial" w:cs="Arial"/><w:sz w:val="18"/><w:szCs w:val="18"/></w:rPr><w:t>Please see http://www.HL7.org/legal/ippolicy.cfm for the full license terms governing the Material.</w:t></w:r></w:p><w:p w14:paraId="6EAAA328" w14:textId="77777777" w:rsidR="00103634" w:rsidRPr="00103634" w:rsidRDefault="00103634" w:rsidP="00103634"><w:pPr><w:rPr><w:rFonts w:ascii="Arial" w:hAnsi="Arial" w:cs="Arial"/><w:sz w:val="18"/><w:szCs w:val="18"/></w:rPr></w:pPr></w:p><w:p w14:paraId="23421C8F" w14:textId="77777777" w:rsidR="00103634" w:rsidRPr="00103634" w:rsidRDefault="00103634" w:rsidP="00103634"><w:pPr><w:rPr><w:rStyle w:val="Strong"/><w:rFonts w:ascii="Arial" w:hAnsi="Arial" w:cs="Arial"/><w:b w:val="0"/><w:color w:val="000000"/><w:sz w:val="18"/><w:szCs w:val="18"/></w:rPr></w:pPr><w:r w:rsidRPr="00103634"><w:rPr><w:rStyle w:val="Strong"/><w:rFonts w:ascii="Arial" w:hAnsi="Arial" w:cs="Arial"/><w:color w:val="000000"/><w:sz w:val="18"/><w:szCs w:val="18"/></w:rPr><w:t xml:space="preserve">Ownership. </w:t></w:r><w:r w:rsidRPr="00103634"><w:rPr><w:rStyle w:val="Strong"/><w:rFonts w:ascii="Arial" w:hAnsi="Arial" w:cs="Arial"/><w:b w:val="0"/><w:color w:val="000000"/><w:sz w:val="18"/><w:szCs w:val="18"/></w:rPr><w:t xml:space="preserve">Licensee agrees and acknowledges that </w:t></w:r><w:r w:rsidRPr="00103634"><w:rPr><w:rStyle w:val="Strong"/><w:rFonts w:ascii="Arial" w:hAnsi="Arial" w:cs="Arial"/><w:color w:val="000000"/><w:sz w:val="18"/><w:szCs w:val="18"/></w:rPr><w:t xml:space="preserve">HL7 owns </w:t></w:r><w:r w:rsidRPr="00103634"><w:rPr><w:rStyle w:val="Strong"/><w:rFonts w:ascii="Arial" w:hAnsi="Arial" w:cs="Arial"/><w:b w:val="0"/><w:color w:val="000000"/><w:sz w:val="18"/><w:szCs w:val="18"/></w:rPr><w:t xml:space="preserve">all right, title, and interest, in and to the Materials. Licensee shall </w:t></w:r><w:r w:rsidRPr="00103634"><w:rPr><w:rStyle w:val="Strong"/><w:rFonts w:ascii="Arial" w:hAnsi="Arial" w:cs="Arial"/><w:color w:val="000000"/><w:sz w:val="18"/><w:szCs w:val="18"/></w:rPr><w:t>take no action contrary to, or inconsistent with</w:t></w:r><w:r w:rsidRPr="00103634"><w:rPr><w:rStyle w:val="Strong"/><w:rFonts w:ascii="Arial" w:hAnsi="Arial" w:cs="Arial"/><w:b w:val="0"/><w:color w:val="000000"/><w:sz w:val="18"/><w:szCs w:val="18"/></w:rPr><w:t>, the foregoing.</w:t></w:r></w:p><w:p w14:paraId="3A4E6A7F" w14:textId="77777777" w:rsidR="00103634" w:rsidRPr="00103634" w:rsidRDefault="00103634" w:rsidP="00103634"><w:pPr><w:rPr><w:rStyle w:val="Strong"/><w:rFonts w:ascii="Arial" w:hAnsi="Arial" w:cs="Arial"/><w:b w:val="0"/><w:bCs/><w:sz w:val="18"/><w:szCs w:val="18"/></w:rPr></w:pPr></w:p><w:p w14:paraId="6D586E17" w14:textId="77777777" w:rsidR="00103634" w:rsidRPr="00103634" w:rsidRDefault="00103634" w:rsidP="00103634"><w:pPr><w:rPr><w:rFonts w:ascii="Arial" w:hAnsi="Arial" w:cs="Arial"/><w:b/><w:color w:val="000000"/><w:sz w:val="18"/><w:szCs w:val="18"/></w:rPr></w:pPr><w:r w:rsidRPr="00103634"><w:rPr><w:rStyle w:val="Strong"/><w:rFonts w:ascii="Arial" w:hAnsi="Arial" w:cs="Arial"/><w:color w:val="000000"/><w:sz w:val="18"/><w:szCs w:val="18"/></w:rPr><w:t xml:space="preserve">Licensee agrees and acknowledges that HL7 may not own all right, title, and interest, in and to the Materials and that the Materials </w:t></w:r><w:r w:rsidRPr="00103634"><w:rPr><w:rFonts w:ascii="Arial" w:hAnsi="Arial" w:cs="Arial"/><w:b/><w:color w:val="000000"/><w:sz w:val="18"/><w:szCs w:val="18"/></w:rPr><w:t>may contain and/or reference intellectual property owned by third parties (“Third Party IP”).  Acceptance of these License Terms does not grant Licensee any rights with respect to Third Party IP. Licensee alone is responsible for identifying and obtaining any necessary licenses or authorizations to utilize Third Party IP in connection with the Materials or otherwise. Any actions, claims or suits brought by a third party resulting from a breach of any Third Party IP right by the Licensee remains the Licensee’s liability.</w:t></w:r></w:p><w:p w14:paraId="74844E08" w14:textId="77777777" w:rsidR="00103634" w:rsidRPr="0019015F" w:rsidRDefault="00103634" w:rsidP="00103634"><w:pPr><w:rPr><w:rFonts w:ascii="Arial" w:hAnsi="Arial" w:cs="Arial"/><w:color w:val="000000"/><w:sz w:val="18"/><w:szCs w:val="18"/></w:rPr></w:pPr></w:p><w:p w14:paraId="12B2757B" w14:textId="77777777" w:rsidR="00103634" w:rsidRPr="0019015F" w:rsidRDefault="00103634" w:rsidP="00103634"><w:pPr><w:rPr><w:rFonts w:ascii="Arial" w:hAnsi="Arial" w:cs="Arial"/><w:color w:val="000000"/><w:sz w:val="18"/><w:szCs w:val="18"/></w:rPr></w:pPr><w:r w:rsidRPr="0019015F"><w:rPr><w:rFonts w:ascii="Arial" w:hAnsi="Arial" w:cs="Arial"/><w:color w:val="000000"/><w:sz w:val="18"/><w:szCs w:val="18"/></w:rPr><w:t>Following is a non-exhaustive list of third-party terminologies that may require a separate license:</w:t></w:r></w:p><w:tbl><w:tblPr><w:tblW w:w="0" w:type="auto"/><w:tblBorders><w:top w:val="single" w:sz="4" w:space="0" w:color="auto"/><w:left w:val="single" w:sz="4" w:space="0" w:color="auto"/><w:bottom w:val="single" w:sz="4" w:space="0" w:color="auto"/><w:right w:val="single" w:sz="4" w:space="0" w:color="auto"/><w:insideH w:val="single" w:sz="4" w:space="0" w:color="auto"/><w:insideV w:val="single" w:sz="4" w:space="0" w:color="auto"/></w:tblBorders><w:tblLook w:val="04A0" w:firstRow="1" w:lastRow="0" w:firstColumn="1" w:lastColumn="0" w:noHBand="0" w:noVBand="1"/></w:tblPr><w:tblGrid><w:gridCol w:w="3330"/><w:gridCol w:w="5778"/></w:tblGrid><w:tr w:rsidR="00103634" w:rsidRPr="0019015F" w14:paraId="0F081DEB" w14:textId="77777777" w:rsidTr="00103634"><w:trPr><w:cantSplit/><w:trHeight w:val="143"/><w:tblHeader/></w:trPr><w:tc><w:tcPr><w:tcW w:w="3330" w:type="dxa"/></w:tcPr><w:p w14:paraId="6351AACD" w14:textId="77777777" w:rsidR="00103634" w:rsidRPr="003A5F81" w:rsidRDefault="00103634" w:rsidP="00F13225"><w:pPr><w:rPr><w:rFonts w:ascii="Arial" w:hAnsi="Arial" w:cs="Arial"/><w:b/><w:color w:val="000000"/><w:sz w:val="18"/><w:szCs w:val="18"/></w:rPr></w:pPr><w:r w:rsidRPr="003A5F81"><w:rPr><w:rFonts w:ascii="Arial" w:hAnsi="Arial" w:cs="Arial"/><w:b/><w:color w:val="000000"/><w:sz w:val="18"/><w:szCs w:val="18"/></w:rPr><w:t>Terminology</w:t></w:r></w:p></w:tc><w:tc><w:tcPr><w:tcW w:w="5778" w:type="dxa"/></w:tcPr><w:p w14:paraId="4F126060" w14:textId="77777777" w:rsidR="00103634" w:rsidRPr="003A5F81" w:rsidRDefault="00103634" w:rsidP="00F13225"><w:pPr><w:spacing w:after="100" w:afterAutospacing="1"/><w:rPr><w:rFonts w:ascii="Arial" w:hAnsi="Arial" w:cs="Arial"/><w:b/><w:color w:val="000000"/><w:sz w:val="18"/><w:szCs w:val="18"/></w:rPr></w:pPr><w:r w:rsidRPr="003A5F81"><w:rPr><w:rFonts w:ascii="Arial" w:hAnsi="Arial" w:cs="Arial"/><w:b/><w:color w:val="000000"/><w:sz w:val="18"/><w:szCs w:val="18"/></w:rPr><w:t>Owner/Contact</w:t></w:r></w:p></w:tc></w:tr><w:tr w:rsidR="00103634" w:rsidRPr="0019015F" w14:paraId="6B5EC66B" w14:textId="77777777" w:rsidTr="00103634"><w:trPr><w:cantSplit/></w:trPr><w:tc><w:tcPr><w:tcW w:w="3330" w:type="dxa"/></w:tcPr><w:p w14:paraId="45706815" w14:textId="77777777" w:rsidR="00103634" w:rsidRPr="003A5F81" w:rsidRDefault="00103634" w:rsidP="00103634"><w:pPr><w:spacing w:after="100" w:afterAutospacing="1"/><w:jc w:val="left"/><w:rPr><w:rFonts w:ascii="Arial" w:hAnsi="Arial" w:cs="Arial"/><w:color w:val="000000"/><w:sz w:val="18"/><w:szCs w:val="20"/></w:rPr></w:pPr><w:r w:rsidRPr="003A5F81"><w:rPr><w:rFonts w:ascii="Arial" w:hAnsi="Arial" w:cs="Arial"/><w:color w:val="000000"/><w:sz w:val="18"/><w:szCs w:val="20"/></w:rPr><w:t>Current Procedures Terminology (CPT) code set</w:t></w:r></w:p></w:tc><w:tc><w:tcPr><w:tcW w:w="5778" w:type="dxa"/></w:tcPr><w:p w14:paraId="0455D1D0" w14:textId="77777777" w:rsidR="00103634" w:rsidRPr="003A5F81" w:rsidRDefault="00103634" w:rsidP="00103634"><w:pPr><w:spacing w:before="100" w:beforeAutospacing="1" w:after="100" w:afterAutospacing="1"/><w:jc w:val="left"/><w:rPr><w:rFonts w:ascii="Arial" w:hAnsi="Arial" w:cs="Arial"/><w:color w:val="000000"/><w:sz w:val="18"/><w:szCs w:val="20"/></w:rPr></w:pPr><w:r w:rsidRPr="003A5F81"><w:rPr><w:rFonts w:ascii="Arial" w:hAnsi="Arial" w:cs="Arial"/><w:color w:val="000000"/><w:sz w:val="18"/><w:szCs w:val="20"/></w:rPr><w:t>American Medical Association</w:t></w:r><w:r w:rsidRPr="003A5F81"><w:rPr><w:rFonts w:ascii="Arial" w:hAnsi="Arial" w:cs="Arial"/><w:color w:val="000000"/><w:sz w:val="18"/><w:szCs w:val="20"/></w:rPr><w:br/><w:t>https://www.ama-assn.org/practice-management/cpt-licensing</w:t></w:r></w:p></w:tc></w:tr><w:tr w:rsidR="00103634" w:rsidRPr="0019015F" w14:paraId="2B546876" w14:textId="77777777" w:rsidTr="00103634"><w:tc><w:tcPr><w:tcW w:w="3330" w:type="dxa"/></w:tcPr><w:p w14:paraId="2DEED701" w14:textId="77777777" w:rsidR="00103634" w:rsidRPr="003A5F81" w:rsidRDefault="00103634" w:rsidP="00103634"><w:pPr><w:spacing w:before="100" w:beforeAutospacing="1" w:after="100" w:afterAutospacing="1"/><w:jc w:val="left"/><w:rPr><w:rFonts w:ascii="Arial" w:hAnsi="Arial" w:cs="Arial"/><w:color w:val="000000"/><w:sz w:val="18"/><w:szCs w:val="20"/></w:rPr></w:pPr><w:r w:rsidRPr="003A5F81"><w:rPr><w:rFonts w:ascii="Arial" w:hAnsi="Arial" w:cs="Arial"/><w:color w:val="000000"/><w:sz w:val="18"/><w:szCs w:val="20"/></w:rPr><w:t>SNOMED CT</w:t></w:r></w:p></w:tc><w:tc><w:tcPr><w:tcW w:w="5778" w:type="dxa"/></w:tcPr><w:p w14:paraId="3EBB1D00" w14:textId="77777777" w:rsidR="00103634" w:rsidRPr="003A5F81" w:rsidRDefault="00103634" w:rsidP="00103634"><w:pPr><w:spacing w:before="100" w:beforeAutospacing="1" w:after="100" w:afterAutospacing="1"/><w:jc w:val="left"/><w:rPr><w:rFonts w:ascii="Arial" w:hAnsi="Arial" w:cs="Arial"/><w:color w:val="000000"/><w:sz w:val="18"/><w:szCs w:val="20"/></w:rPr></w:pPr><w:r w:rsidRPr="003A5F81"><w:rPr><w:rFonts w:ascii="Arial" w:hAnsi="Arial" w:cs="Arial"/><w:color w:val="000000"/><w:sz w:val="18"/><w:szCs w:val="20"/></w:rPr><w:t xml:space="preserve">SNOMED International   </w:t></w:r><w:r w:rsidRPr="003A5F81"><w:rPr><w:rFonts w:ascii="Arial" w:hAnsi="Arial" w:cs="Arial"/><w:sz w:val="18"/><w:szCs w:val="20"/></w:rPr><w:t>http://www.snomed.org/snomed-ct/get-snomed-ct</w:t></w:r><w:r w:rsidRPr="003A5F81"><w:rPr><w:rFonts w:ascii="Arial" w:hAnsi="Arial" w:cs="Arial"/><w:color w:val="000000"/><w:sz w:val="18"/><w:szCs w:val="20"/></w:rPr><w:t xml:space="preserve"> or info@ihtsdo.org</w:t></w:r></w:p></w:tc></w:tr><w:tr w:rsidR="00103634" w:rsidRPr="0019015F" w14:paraId="1E9BA102" w14:textId="77777777" w:rsidTr="00103634"><w:tc><w:tcPr><w:tcW w:w="3330" w:type="dxa"/></w:tcPr><w:p w14:paraId="60383A14" w14:textId="77777777" w:rsidR="00103634" w:rsidRPr="007D44E5" w:rsidRDefault="00103634" w:rsidP="00103634"><w:pPr><w:spacing w:before="100" w:beforeAutospacing="1" w:after="100" w:afterAutospacing="1"/><w:jc w:val="left"/><w:rPr><w:rFonts w:ascii="Arial" w:hAnsi="Arial" w:cs="Arial"/><w:color w:val="000000"/><w:sz w:val="18"/><w:szCs w:val="20"/><w:lang w:val="fr-FR"/></w:rPr></w:pPr><w:proofErr w:type="spellStart"/><w:r w:rsidRPr="007D44E5"><w:rPr><w:rFonts w:ascii="Arial" w:hAnsi="Arial" w:cs="Arial"/><w:color w:val="000000"/><w:sz w:val="18"/><w:szCs w:val="20"/><w:lang w:val="fr-FR"/></w:rPr><w:t>Logical</w:t></w:r><w:proofErr w:type="spellEnd"/><w:r w:rsidRPr="007D44E5"><w:rPr><w:rFonts w:ascii="Arial" w:hAnsi="Arial" w:cs="Arial"/><w:color w:val="000000"/><w:sz w:val="18"/><w:szCs w:val="20"/><w:lang w:val="fr-FR"/></w:rPr><w:t xml:space="preserve"> Observation </w:t></w:r><w:proofErr w:type="spellStart"/><w:r w:rsidRPr="007D44E5"><w:rPr><w:rFonts w:ascii="Arial" w:hAnsi="Arial" w:cs="Arial"/><w:color w:val="000000"/><w:sz w:val="18"/><w:szCs w:val="20"/><w:lang w:val="fr-FR"/></w:rPr><w:t>Identifiers</w:t></w:r><w:proofErr w:type="spellEnd"/><w:r w:rsidRPr="007D44E5"><w:rPr><w:rFonts w:ascii="Arial" w:hAnsi="Arial" w:cs="Arial"/><w:color w:val="000000"/><w:sz w:val="18"/><w:szCs w:val="20"/><w:lang w:val="fr-FR"/></w:rPr><w:t xml:space="preserve"> </w:t></w:r><w:proofErr w:type="spellStart"/><w:r w:rsidRPr="007D44E5"><w:rPr><w:rFonts w:ascii="Arial" w:hAnsi="Arial" w:cs="Arial"/><w:color w:val="000000"/><w:sz w:val="18"/><w:szCs w:val="20"/><w:lang w:val="fr-FR"/></w:rPr><w:t>Names</w:t></w:r><w:proofErr w:type="spellEnd"/><w:r w:rsidRPr="007D44E5"><w:rPr><w:rFonts w:ascii="Arial" w:hAnsi="Arial" w:cs="Arial"/><w:color w:val="000000"/><w:sz w:val="18"/><w:szCs w:val="20"/><w:lang w:val="fr-FR"/></w:rPr><w:t xml:space="preserve"> &amp; Codes (LOINC)</w:t></w:r></w:p></w:tc><w:tc><w:tcPr><w:tcW w:w="5778" w:type="dxa"/></w:tcPr><w:p w14:paraId="6818E87B" w14:textId="77777777" w:rsidR="00103634" w:rsidRPr="003A5F81" w:rsidRDefault="00103634" w:rsidP="00F13225"><w:pPr><w:spacing w:before="100" w:beforeAutospacing="1" w:after="100" w:afterAutospacing="1"/><w:rPr><w:rFonts w:ascii="Arial" w:hAnsi="Arial" w:cs="Arial"/><w:color w:val="000000"/><w:sz w:val="18"/><w:szCs w:val="20"/></w:rPr></w:pPr><w:proofErr w:type="spellStart"/><w:r w:rsidRPr="003A5F81"><w:rPr><w:rFonts w:ascii="Arial" w:hAnsi="Arial" w:cs="Arial"/><w:color w:val="000000"/><w:sz w:val="18"/><w:szCs w:val="20"/></w:rPr><w:t>Regenstrief</w:t></w:r><w:proofErr w:type="spellEnd"/><w:r w:rsidRPr="003A5F81"><w:rPr><w:rFonts w:ascii="Arial" w:hAnsi="Arial" w:cs="Arial"/><w:color w:val="000000"/><w:sz w:val="18"/><w:szCs w:val="20"/></w:rPr><w:t xml:space="preserve"> Institute</w:t></w:r></w:p></w:tc></w:tr><w:tr w:rsidR="00103634" w:rsidRPr="0019015F" w14:paraId="3426AAD4" w14:textId="77777777" w:rsidTr="00103634"><w:tc><w:tcPr><w:tcW w:w="3330" w:type="dxa"/></w:tcPr><w:p w14:paraId="537C99E6" w14:textId="77777777" w:rsidR="00103634" w:rsidRPr="003A5F81" w:rsidRDefault="00103634" w:rsidP="00103634"><w:pPr><w:spacing w:before="100" w:beforeAutospacing="1" w:after="100" w:afterAutospacing="1"/><w:jc w:val="left"/><w:rPr><w:rFonts w:ascii="Arial" w:hAnsi="Arial" w:cs="Arial"/><w:color w:val="000000"/><w:sz w:val="18"/><w:szCs w:val="20"/></w:rPr></w:pPr><w:r w:rsidRPr="003A5F81"><w:rPr><w:rFonts w:ascii="Arial" w:hAnsi="Arial" w:cs="Arial"/><w:color w:val="000000"/><w:sz w:val="18"/><w:szCs w:val="20"/></w:rPr><w:t>International Classification of Diseases (ICD) codes</w:t></w:r></w:p></w:tc><w:tc><w:tcPr><w:tcW w:w="5778" w:type="dxa"/></w:tcPr><w:p w14:paraId="6E28F407" w14:textId="77777777" w:rsidR="00103634" w:rsidRPr="003A5F81" w:rsidRDefault="00103634" w:rsidP="00F13225"><w:pPr><w:spacing w:before="100" w:beforeAutospacing="1" w:after="100" w:afterAutospacing="1"/><w:rPr><w:rFonts w:ascii="Arial" w:hAnsi="Arial" w:cs="Arial"/><w:color w:val="000000"/><w:sz w:val="18"/><w:szCs w:val="20"/></w:rPr></w:pPr><w:r w:rsidRPr="003A5F81"><w:rPr><w:rFonts w:ascii="Arial" w:hAnsi="Arial" w:cs="Arial"/><w:color w:val="000000"/><w:sz w:val="18"/><w:szCs w:val="20"/></w:rPr><w:t>World Health Organization (WHO)</w:t></w:r></w:p></w:tc></w:tr><w:tr w:rsidR="00103634" w:rsidRPr="00F323C1" w14:paraId="31E42750" w14:textId="77777777" w:rsidTr="00103634"><w:tc><w:tcPr><w:tcW w:w="3330" w:type="dxa"/></w:tcPr><w:p w14:paraId="4A744B46" w14:textId="77777777" w:rsidR="00103634" w:rsidRPr="003A5F81" w:rsidRDefault="00103634" w:rsidP="00103634"><w:pPr><w:spacing w:before="100" w:beforeAutospacing="1" w:after="100" w:afterAutospacing="1"/><w:jc w:val="left"/><w:rPr><w:rFonts w:ascii="Arial" w:hAnsi="Arial" w:cs="Arial"/><w:color w:val="000000"/><w:sz w:val="18"/><w:szCs w:val="20"/></w:rPr></w:pPr><w:r w:rsidRPr="003A5F81"><w:rPr><w:rFonts w:ascii="Arial" w:hAnsi="Arial" w:cs="Arial"/><w:iCs/><w:color w:val="000000"/><w:sz w:val="18"/><w:szCs w:val="20"/></w:rPr><w:t>NUCC Health Care Provider Taxonomy code set</w:t></w:r></w:p></w:tc><w:tc><w:tcPr><w:tcW w:w="5778" w:type="dxa"/></w:tcPr><w:p w14:paraId="6A78A879" w14:textId="77777777" w:rsidR="00103634" w:rsidRPr="003A5F81" w:rsidRDefault="00103634" w:rsidP="00103634"><w:pPr><w:spacing w:before="100" w:beforeAutospacing="1" w:after="100" w:afterAutospacing="1"/><w:jc w:val="left"/><w:rPr><w:rFonts w:ascii="Arial" w:hAnsi="Arial" w:cs="Arial"/><w:color w:val="000000"/><w:sz w:val="18"/><w:szCs w:val="20"/></w:rPr></w:pPr><w:r w:rsidRPr="003A5F81"><w:rPr><w:rFonts w:ascii="Arial" w:hAnsi="Arial" w:cs="Arial"/><w:iCs/><w:color w:val="000000"/><w:sz w:val="18"/><w:szCs w:val="20"/></w:rPr><w:t xml:space="preserve">American Medical Association. Please see </w:t></w:r><w:bookmarkStart w:id="1" w:name="OLE_LINK1"/><w:r w:rsidRPr="003A5F81"><w:rPr><w:rFonts w:ascii="Arial" w:hAnsi="Arial" w:cs="Arial"/><w:iCs/><w:color w:val="000000"/><w:sz w:val="18"/><w:szCs w:val="20"/></w:rPr><w:t>www.nucc.org. AMA licensing contact: 312-464-5022 (AMA IP services)</w:t></w:r><w:bookmarkEnd w:id="1"/></w:p></w:tc></w:tr></w:tbl><w:p w14:paraId="18C4FD7C" w14:textId="77777777" w:rsidR="00103634" w:rsidRPr="00655E67" w:rsidRDefault="00103634" w:rsidP="00DA5426"><w:pPr><w:spacing w:after="100"/><w:rPr><w:color w:val="000000"/><w:kern w:val="0"/><w:sz w:val="18"/><w:szCs w:val="18"/><w:lang w:eastAsia="en-US"/></w:rPr></w:pPr></w:p><w:p w14:paraId="583D3438" w14:textId="77777777" w:rsidR="008A4D08" w:rsidRDefault="008A4D08" w:rsidP="00DA5426"><w:pPr><w:pStyle w:val="Header"/><w:ind w:left="0" w:firstLine="0"/></w:pPr><w:bookmarkStart w:id="2" w:name="_Toc207005766"/><w:bookmarkStart w:id="3" w:name="_Toc211048979"/><w:bookmarkStart w:id="4" w:name="_Toc210996266"/><w:bookmarkEnd w:id="2"/><w:bookmarkEnd w:id="3"/><w:bookmarkEnd w:id="4"/></w:p><w:p w14:paraId="3F092EB2" w14:textId="77777777" w:rsidR="00DA5426" w:rsidRPr="00DA42BC" w:rsidRDefault="00DA5426" w:rsidP="006B4359"><w:pPr><w:pStyle w:val="Header"/><w:ind w:left="0" w:firstLine="0"/><w:outlineLvl w:val="0"/></w:pPr><w:r w:rsidRPr="00655E67"><w:t>Acknowledgments</w:t></w:r></w:p><w:p w14:paraId="5E514126" w14:textId="77777777" w:rsidR="00DA5426" w:rsidRPr="00AA2588" w:rsidRDefault="00DA5426" w:rsidP="00DA5426"><w:bookmarkStart w:id="5" w:name="_Hlk502932509"/><w:r w:rsidRPr="00AA2588"><w:t xml:space="preserve">The authors of this document wish to recognize the following participants who contributed their time and expertise </w:t></w:r><w:r w:rsidR="00B70A8D"><w:t>to the development of this specification</w:t></w:r><w:r w:rsidRPr="00AA2588"><w:t>.</w:t></w:r></w:p><w:tbl><w:tblPr><w:tblW w:w="8640" w:type="dxa"/><w:jc w:val="center"/><w:tblBorders><w:top w:val="single" w:sz="12" w:space="0" w:color="C00000"/><w:left w:val="single" w:sz="12" w:space="0" w:color="D9D9D9" w:themeColor="background1" w:themeShade="D9"/><w:bottom w:val="single" w:sz="12" w:space="0" w:color="C00000"/><w:right w:val="single" w:sz="12" w:space="0" w:color="D9D9D9" w:themeColor="background1" w:themeShade="D9"/><w:insideH w:val="single" w:sz="12" w:space="0" w:color="C00000"/><w:insideV w:val="single" w:sz="12" w:space="0" w:color="D9D9D9" w:themeColor="background1" w:themeShade="D9"/></w:tblBorders><w:tblCellMar><w:top w:w="14" w:type="dxa"/><w:left w:w="115" w:type="dxa"/><w:bottom w:w="14" w:type="dxa"/><w:right w:w="115" w:type="dxa"/></w:tblCellMar><w:tblLook w:val="0000" w:firstRow="0" w:lastRow="0" w:firstColumn="0" w:lastColumn="0" w:noHBand="0" w:noVBand="0"/></w:tblPr><w:tblGrid><w:gridCol w:w="3025"/><w:gridCol w:w="5615"/></w:tblGrid><w:tr w:rsidR="00DA5426" w:rsidRPr="00655E67" w14:paraId="5BD69EC4" w14:textId="77777777" w:rsidTr="00AD38F4"><w:trPr><w:cantSplit/><w:trHeight w:val="254"/><w:jc w:val="center"/></w:trPr><w:tc><w:tcPr><w:tcW w:w="3025" w:type="dxa"/><w:shd w:val="clear" w:color="auto" w:fill="auto"/></w:tcPr><w:bookmarkEnd w:id="5"/><w:p w14:paraId="6E3D2A84" w14:textId="77777777" w:rsidR="00DA5426" w:rsidRPr="002F0B20" w:rsidRDefault="00DA5426" w:rsidP="00AD38F4"><w:pPr><w:pStyle w:val="TableContent"/><w:spacing w:before="0" w:after="0"/><w:jc w:val="left"/><w:rPr><w:highlight w:val="yellow"/></w:rPr></w:pPr><w:r><w:t>Craig Newman</w:t></w:r></w:p></w:tc><w:tc><w:tcPr><w:tcW w:w="5615" w:type="dxa"/><w:shd w:val="clear" w:color="auto" w:fill="auto"/></w:tcPr><w:p w14:paraId="3B94F061" w14:textId="77777777" w:rsidR="00DA5426" w:rsidRPr="00236E3E" w:rsidRDefault="00DE0376" w:rsidP="00AD38F4"><w:pPr><w:pStyle w:val="TableContent"/><w:spacing w:before="0" w:after="0"/><w:jc w:val="left"/><w:rPr><w:highlight w:val="yellow"/></w:rPr></w:pPr><w:r w:rsidRPr="00DE0376"><w:t>Altarum</w:t></w:r></w:p></w:tc></w:tr><w:tr w:rsidR="005A532C" w:rsidRPr="00655E67" w14:paraId="70429A9F" w14:textId="77777777" w:rsidTr="00AD38F4"><w:trPr><w:cantSplit/><w:trHeight w:val="254"/><w:jc w:val="center"/></w:trPr><w:tc><w:tcPr><w:tcW w:w="3025" w:type="dxa"/><w:shd w:val="clear" w:color="auto" w:fill="auto"/></w:tcPr><w:p w14:paraId="5395A3C3" w14:textId="77777777" w:rsidR="005A532C" w:rsidRPr="00AD38F4" w:rsidRDefault="005A532C" w:rsidP="005A532C"><w:pPr><w:pStyle w:val="TableContent"/><w:spacing w:before="0" w:after="0"/><w:jc w:val="left"/><w:rPr><w:color w:val="auto"/></w:rPr></w:pPr><w:r><w:t>Caroline Rosin</w:t></w:r></w:p></w:tc><w:tc><w:tcPr><w:tcW w:w="5615" w:type="dxa"/><w:shd w:val="clear" w:color="auto" w:fill="auto"/></w:tcPr><w:p w14:paraId="2EB85286" w14:textId="77777777" w:rsidR="005A532C" w:rsidRPr="00655E67" w:rsidRDefault="005A532C" w:rsidP="005A532C"><w:pPr><w:pStyle w:val="TableContent"/><w:spacing w:before="0" w:after="0"/><w:jc w:val="left"/></w:pPr><w:r><w:t>National Institute of Standards and Technology (NIST)</w:t></w:r></w:p></w:tc></w:tr><w:tr w:rsidR="005A532C" w:rsidRPr="00655E67" w14:paraId="55539D2A" w14:textId="77777777" w:rsidTr="00AD38F4"><w:trPr><w:cantSplit/><w:trHeight w:val="254"/><w:jc w:val="center"/></w:trPr><w:tc><w:tcPr><w:tcW w:w="3025" w:type="dxa"/><w:shd w:val="clear" w:color="auto" w:fill="auto"/></w:tcPr><w:p w14:paraId="4632AB97" w14:textId="77777777" w:rsidR="005A532C" w:rsidRPr="00AD38F4" w:rsidRDefault="00DE57E8" w:rsidP="005A532C"><w:pPr><w:pStyle w:val="TableContent"/><w:spacing w:before="0" w:after="0"/><w:jc w:val="left"/><w:rPr><w:color w:val="auto"/></w:rPr></w:pPr><w:r><w:rPr><w:color w:val="auto"/></w:rPr><w:t>Hossam Tamri</w:t></w:r></w:p></w:tc><w:tc><w:tcPr><w:tcW w:w="5615" w:type="dxa"/><w:shd w:val="clear" w:color="auto" w:fill="auto"/></w:tcPr><w:p w14:paraId="20ED9401" w14:textId="77777777" w:rsidR="005A532C" w:rsidRPr="00655E67" w:rsidRDefault="007215EE" w:rsidP="005A532C"><w:pPr><w:pStyle w:val="TableContent"/><w:spacing w:before="0" w:after="0"/><w:jc w:val="left"/></w:pPr><w:r><w:t>National Institute of Standards and Technology (NIST)</w:t></w:r></w:p></w:tc></w:tr><w:tr w:rsidR="005A532C" w:rsidRPr="00655E67" w14:paraId="62A576F9" w14:textId="77777777" w:rsidTr="00AD38F4"><w:trPr><w:cantSplit/><w:trHeight w:val="254"/><w:jc w:val="center"/></w:trPr><w:tc><w:tcPr><w:tcW w:w="3025" w:type="dxa"/><w:shd w:val="clear" w:color="auto" w:fill="auto"/></w:tcPr><w:p w14:paraId="03C133F2" w14:textId="77777777" w:rsidR="005A532C" w:rsidRPr="00AD38F4" w:rsidRDefault="00DE57E8" w:rsidP="005A532C"><w:pPr><w:pStyle w:val="TableContent"/><w:spacing w:before="0" w:after="0"/><w:jc w:val="left"/><w:rPr><w:color w:val="auto"/></w:rPr></w:pPr><w:r w:rsidRPr="00DE57E8"><w:rPr><w:color w:val="auto"/></w:rPr><w:t>Sheryl Taylor</w:t></w:r></w:p></w:tc><w:tc><w:tcPr><w:tcW w:w="5615" w:type="dxa"/><w:shd w:val="clear" w:color="auto" w:fill="auto"/></w:tcPr><w:p w14:paraId="25F27CAB" w14:textId="77777777" w:rsidR="005A532C" w:rsidRPr="00655E67" w:rsidRDefault="00DE57E8" w:rsidP="005A532C"><w:pPr><w:pStyle w:val="TableContent"/><w:spacing w:before="0" w:after="0"/><w:jc w:val="left"/></w:pPr><w:r w:rsidRPr="00DE57E8"><w:t>National Institute of Standards and Technology (NIST)</w:t></w:r></w:p></w:tc></w:tr></w:tbl><w:p w14:paraId="00D219E9" w14:textId="77777777" w:rsidR="00FD0DF9" w:rsidRDefault="00FD0DF9" w:rsidP="00FD0DF9"/><w:p w14:paraId="17389EE4" w14:textId="77777777" w:rsidR="00FD0DF9" w:rsidRDefault="00B63EEC" w:rsidP="00FD0DF9"><w:r><w:t>Portions</w:t></w:r><w:r w:rsidR="00A27C0A"><w:t xml:space="preserve"> of this document </w:t></w:r><w:r w:rsidR="001D7D9C"><w:t xml:space="preserve">were </w:t></w:r><w:r w:rsidR="00A27C0A"><w:t xml:space="preserve">adopted </w:t></w:r><w:r w:rsidR="00627773" w:rsidRPr="00627773"><w:t>(“as</w:t></w:r><w:r w:rsidR="00BE6049"><w:t>-</w:t></w:r><w:r w:rsidR="00627773" w:rsidRPr="00627773"><w:t xml:space="preserve">is” or “revised”) </w:t></w:r><w:r w:rsidR="00627773"><w:t>from external sources. These</w:t></w:r><w:r w:rsidR="00FD0DF9"><w:t xml:space="preserve"> include:</w:t></w:r></w:p><w:p w14:paraId="723460DA" w14:textId="77777777" w:rsidR="00B63EEC" w:rsidRDefault="00B63EEC" w:rsidP="001E3157"><w:pPr><w:pStyle w:val="ListParagraph"/><w:numPr><w:ilvl w:val="0"/><w:numId w:val="27"/></w:numPr></w:pPr><w:r><w:t>Healthcare Interoperability Standards Compliance Handbook. F. Oemig, R. Snelick 2016.</w:t></w:r></w:p><w:p w14:paraId="5E74703C" w14:textId="77777777" w:rsidR="00FD0DF9" w:rsidRDefault="00FD0DF9" w:rsidP="001E3157"><w:pPr><w:pStyle w:val="ListParagraph"/><w:numPr><w:ilvl w:val="0"/><w:numId w:val="27"/></w:numPr></w:pPr><w:r><w:t>HL7 v2.8.</w:t></w:r><w:r w:rsidR="00B63EEC"><w:t>2</w:t></w:r><w:r><w:t xml:space="preserve"> Chapter 2B Control: Conformance</w:t></w:r></w:p><w:p w14:paraId="340298B8" w14:textId="77777777" w:rsidR="007215EE" w:rsidRDefault="00E43682" w:rsidP="001E3157"><w:pPr><w:pStyle w:val="ListParagraph"/><w:numPr><w:ilvl w:val="0"/><w:numId w:val="27"/></w:numPr></w:pPr><w:r><w:t xml:space="preserve">Selected </w:t></w:r><w:r w:rsidR="00535C15"><w:t>HL7 v2 Balloted Implementation Guides</w:t></w:r></w:p><w:p w14:paraId="62A9AC66" w14:textId="77777777" w:rsidR="00523E6F" w:rsidRPr="00B63EEC" w:rsidRDefault="00523E6F" w:rsidP="001E3157"><w:pPr><w:pStyle w:val="ListParagraph"/><w:numPr><w:ilvl w:val="0"/><w:numId w:val="27"/></w:numPr></w:pPr><w:r><w:t>Specifications and materials created by the National Institute of Standards and Technology</w:t></w:r></w:p><w:p w14:paraId="2247B1ED" w14:textId="77777777" w:rsidR="00DA5426" w:rsidRPr="00655E67" w:rsidRDefault="00DA5426" w:rsidP="00FD0DF9"><w:pPr><w:rPr><w:sz w:val="36"/></w:rPr></w:pPr><w:r w:rsidRPr="00655E67"><w:br w:type="page"/></w:r></w:p><w:p w14:paraId="3381A804" w14:textId="77777777" w:rsidR="00DA5426" w:rsidRPr="00655E67" w:rsidRDefault="00DA5426" w:rsidP="006B4359"><w:pPr><w:pStyle w:val="Header"/><w:spacing w:before="0"/><w:ind w:left="0" w:firstLine="0"/><w:outlineLvl w:val="0"/></w:pPr><w:r w:rsidRPr="00655E67"><w:lastRenderedPageBreak/><w:t>Copyrights</w:t></w:r></w:p><w:p w14:paraId="6C122B69" w14:textId="77777777" w:rsidR="006B4359" w:rsidRPr="00655E67" w:rsidRDefault="006B4359" w:rsidP="006B4359"><w:bookmarkStart w:id="6" w:name="_Toc207005872"/><w:bookmarkStart w:id="7" w:name="_Ref207089931"/><w:bookmarkStart w:id="8" w:name="_Toc211049006"/><w:bookmarkStart w:id="9" w:name="_Toc210996292"/><w:r w:rsidRPr="00655E67"><w:t>This material includes SNOMED Clinical Terms ® (SNOMED CT®)</w:t></w:r><w:r><w:t>,</w:t></w:r><w:r w:rsidRPr="00655E67"><w:t xml:space="preserve"> which is used by permission of the International Health Terminology Standards Development Organization (IHTSDO). All rights reserved. SNOMED CT was originally created by The College of American Pathologists. "SNOMED ®" and "SNOMED CT ®" are registered trademarks of the IHTSDO.</w:t></w:r></w:p><w:p w14:paraId="10185B93" w14:textId="77777777" w:rsidR="006B4359" w:rsidRPr="00655E67" w:rsidRDefault="006B4359" w:rsidP="006B4359"><w:r w:rsidRPr="00655E67"><w:t>This material contains content from LOINC® (</w:t></w:r><w:hyperlink r:id="rId11" w:history="1"><w:r w:rsidRPr="00DA42BC"><w:rPr><w:rStyle w:val="Hyperlink"/><w:rFonts w:ascii="Times New Roman" w:hAnsi="Times New Roman"/><w:sz w:val="24"/></w:rPr><w:t>http://loinc.org</w:t></w:r></w:hyperlink><w:r w:rsidRPr="00655E67"><w:t>). The LOINC table, LOINC codes, and LOINC panels and forms file are copyright (c) 1995-201</w:t></w:r><w:r w:rsidRPr="00DA42BC"><w:t xml:space="preserve">3, </w:t></w:r><w:proofErr w:type="spellStart"/><w:r w:rsidRPr="00DA42BC"><w:t>Regenstrief</w:t></w:r><w:proofErr w:type="spellEnd"/><w:r w:rsidRPr="00DA42BC"><w:t xml:space="preserve"> Institute, Inc. and the Logical Observation Identifiers Names and Codes (LOINC) Committee and available at no cost under the license at </w:t></w:r><w:hyperlink r:id="rId12" w:history="1"><w:r w:rsidRPr="00DA42BC"><w:rPr><w:rStyle w:val="Hyperlink"/><w:rFonts w:ascii="Times New Roman" w:hAnsi="Times New Roman"/><w:sz w:val="24"/></w:rPr><w:t>http://loinc.org/terms-of-use</w:t></w:r></w:hyperlink><w:r w:rsidRPr="00655E67"><w:t>.</w:t></w:r></w:p><w:p w14:paraId="7733ED68" w14:textId="77777777" w:rsidR="00773316" w:rsidRDefault="00773316" w:rsidP="00773316"><w:bookmarkStart w:id="10" w:name="_GoBack"/><w:bookmarkEnd w:id="10"/></w:p><w:p w14:paraId="59E1C2F3" w14:textId="77777777" w:rsidR="00773316" w:rsidRDefault="00773316" w:rsidP="00773316"/><w:bookmarkEnd w:id="6"/><w:bookmarkEnd w:id="7"/><w:bookmarkEnd w:id="8"/><w:bookmarkEnd w:id="9"/><w:sectPr w:rsidR="00773316" w:rsidSect="00C7736F"><w:headerReference w:type="even" r:id="rId13"/><w:headerReference w:type="default" r:id="rId14"/><w:footerReference w:type="even" r:id="rId15"/><w:headerReference w:type="first" r:id="rId16"/><w:pgSz w:w="12240" w:h="15840"/><w:pgMar w:top="1440" w:right="1440" w:bottom="1440" w:left="1440" w:header="720" w:footer="720" w:gutter="0"/><w:cols w:space="720"/><w:docGrid w:linePitch="360"/></w:sectPr></w:body></w:document>