<?xml version="1.0" encoding="utf-8"?>
<SegmentDefinition>
  <url value="http://hl7.org/v2plus/SegmentDefinition/allergy-reaction-segment"/>
  <name value="Allergy Reaction Segment"/>
  <withdrawn value="false"/>
  <abbreviation value="IAR"/>
  <description>
    <status value="additional"/>
    <div>
      <description>
        <status value="additional"/>
        <div>
          <p>
            <strong>The IAR segment is used to transmit a single reaction and information associated with this single reaction occurrence for a particular patient allergy (IAM – patient adverse reaction).</strong>
          </p>
          <p>
            <strong>HL7 Attribute Table – IAR – allergy reaction</strong>
          </p>
        </div>
      </description>
    </div>
  </description>
  <field>
    <sequenceNumber value="1"/>
    <mustSupport value="true"/>
    <minCardinality value="1">
      <maxCardinality value="1">
        <dataElement value="https://www.hl7.org/v2plus/DataElementDefinition/03296"/>
      </maxCardinality>
    </minCardinality>
  </field>
  <field>
    <sequenceNumber value="2"/>
    <mustSupport value="true"/>
    <minCardinality value="1">
      <maxCardinality value="1">
        <dataElement value="https://www.hl7.org/v2plus/DataElementDefinition/03297"/>
      </maxCardinality>
    </minCardinality>
  </field>
  <field>
    <sequenceNumber value="3"/>
    <mustSupport value="false"/>
    <minCardinality value="0">
      <maxCardinality value="1">
        <dataElement value="https://www.hl7.org/v2plus/DataElementDefinition/03298"/>
      </maxCardinality>
    </minCardinality>
  </field>
  <field>
    <sequenceNumber value="4"/>
    <mustSupport value="false"/>
    <minCardinality value="0">
      <maxCardinality value="1">
        <dataElement value="https://www.hl7.org/v2plus/DataElementDefinition/03299"/>
      </maxCardinality>
    </minCardinality>
  </field>
</SegmentDefinition>
