<?xml version="1.0" encoding="utf-8"?>
<SegmentDefinition>
  <url value="http://hl7.org/v2plus/SegmentDefinition/blood-product-transfusion-disposition-segment"/>
  <name value="Blood Product Transfusion/Disposition Segment"/>
  <withdrawn value="false"/>
  <abbreviation value="BTX"/>
  <description>
    <status value="additional"/>
    <div>
      <description>
        <status value="additional"/>
        <div>
          <p>HL7 Attribute Table – BTX – Blood Product Transfusion/Disposition</p>
        </div>
      </description>
    </div>
  </description>
  <field>
    <sequenceNumber value="1"/>
    <mustSupport value="true"/>
    <minCardinality value="1">
      <maxCardinality value="1">
        <dataElement value="https://www.hl7.org/v2plus/DataElementDefinition/01735"/>
      </maxCardinality>
    </minCardinality>
  </field>
  <field>
    <sequenceNumber value="2"/>
    <mustSupport value=""/>
    <maxCardinality value="1">
      <dataElement value="https://www.hl7.org/v2plus/DataElementDefinition/01736"/>
    </maxCardinality>
  </field>
  <field>
    <sequenceNumber value="3"/>
    <mustSupport value=""/>
    <maxCardinality value="1">
      <dataElement value="https://www.hl7.org/v2plus/DataElementDefinition/01737"/>
    </maxCardinality>
  </field>
  <field>
    <sequenceNumber value="4"/>
    <mustSupport value=""/>
    <maxCardinality value="1">
      <dataElement value="https://www.hl7.org/v2plus/DataElementDefinition/01738"/>
    </maxCardinality>
  </field>
  <field>
    <sequenceNumber value="5"/>
    <mustSupport value=""/>
    <maxCardinality value="1">
      <dataElement value="https://www.hl7.org/v2plus/DataElementDefinition/01739"/>
    </maxCardinality>
  </field>
  <field>
    <sequenceNumber value="6"/>
    <mustSupport value=""/>
    <maxCardinality value="1">
      <dataElement value="https://www.hl7.org/v2plus/DataElementDefinition/01740"/>
    </maxCardinality>
  </field>
  <field>
    <sequenceNumber value="7"/>
    <mustSupport value=""/>
    <maxCardinality value="1">
      <dataElement value="https://www.hl7.org/v2plus/DataElementDefinition/01741"/>
    </maxCardinality>
  </field>
  <field>
    <sequenceNumber value="8"/>
    <mustSupport value="true"/>
    <minCardinality value="1">
      <maxCardinality value="1">
        <dataElement value="https://www.hl7.org/v2plus/DataElementDefinition/01742"/>
      </maxCardinality>
    </minCardinality>
  </field>
  <field>
    <sequenceNumber value="9"/>
    <mustSupport value="false"/>
    <minCardinality value="0">
      <maxCardinality value="1">
        <dataElement value="https://www.hl7.org/v2plus/DataElementDefinition/01743"/>
      </maxCardinality>
    </minCardinality>
  </field>
  <field>
    <sequenceNumber value="10"/>
    <mustSupport value="false"/>
    <minCardinality value="0">
      <maxCardinality value="1">
        <dataElement value="https://www.hl7.org/v2plus/DataElementDefinition/01744"/>
      </maxCardinality>
    </minCardinality>
  </field>
  <field>
    <sequenceNumber value="11"/>
    <mustSupport value="true"/>
    <minCardinality value="1">
      <maxCardinality value="1">
        <dataElement value="https://www.hl7.org/v2plus/DataElementDefinition/01745"/>
      </maxCardinality>
    </minCardinality>
  </field>
  <field>
    <sequenceNumber value="12"/>
    <mustSupport value="true"/>
    <minCardinality value="1">
      <maxCardinality value="1">
        <dataElement value="https://www.hl7.org/v2plus/DataElementDefinition/01746"/>
      </maxCardinality>
    </minCardinality>
  </field>
  <field>
    <sequenceNumber value="13"/>
    <mustSupport value="true"/>
    <minCardinality value="1">
      <maxCardinality value="1">
        <dataElement value="https://www.hl7.org/v2plus/DataElementDefinition/01747"/>
      </maxCardinality>
    </minCardinality>
  </field>
  <field>
    <sequenceNumber value="14"/>
    <mustSupport value="false"/>
    <minCardinality value="0">
      <maxCardinality value="1">
        <dataElement value="https://www.hl7.org/v2plus/DataElementDefinition/01748"/>
      </maxCardinality>
    </minCardinality>
  </field>
  <field>
    <sequenceNumber value="15"/>
    <mustSupport value="false"/>
    <minCardinality value="0">
      <maxCardinality value="1">
        <dataElement value="https://www.hl7.org/v2plus/DataElementDefinition/01749"/>
      </maxCardinality>
    </minCardinality>
  </field>
  <field>
    <sequenceNumber value="16"/>
    <mustSupport value="false"/>
    <minCardinality value="0">
      <maxCardinality value="1">
        <dataElement value="https://www.hl7.org/v2plus/DataElementDefinition/01750"/>
      </maxCardinality>
    </minCardinality>
  </field>
  <field>
    <sequenceNumber value="17"/>
    <mustSupport value="false"/>
    <minCardinality value="0">
      <maxCardinality value="1">
        <dataElement value="https://www.hl7.org/v2plus/DataElementDefinition/01751"/>
      </maxCardinality>
    </minCardinality>
  </field>
  <field>
    <sequenceNumber value="18"/>
    <mustSupport value="false"/>
    <minCardinality value="0">
      <dataElement value="https://www.hl7.org/v2plus/DataElementDefinition/01752"/>
    </minCardinality>
  </field>
  <field>
    <sequenceNumber value="19"/>
    <mustSupport value="false"/>
    <minCardinality value="0">
      <maxCardinality value="1">
        <dataElement value="https://www.hl7.org/v2plus/DataElementDefinition/01753"/>
      </maxCardinality>
    </minCardinality>
  </field>
  <field>
    <sequenceNumber value="20"/>
    <mustSupport value="false"/>
    <minCardinality value="0">
      <maxCardinality value="1">
        <dataElement value="https://www.hl7.org/v2plus/DataElementDefinition/03391"/>
      </maxCardinality>
    </minCardinality>
  </field>
  <field>
    <sequenceNumber value="21"/>
    <mustSupport value="false"/>
    <minCardinality value="0">
      <maxCardinality value="1">
        <dataElement value="https://www.hl7.org/v2plus/DataElementDefinition/00816"/>
      </maxCardinality>
    </minCardinality>
  </field>
</SegmentDefinition>
